{
  "id": "angelCloud",
  "name": "Angel cloud",
  "description": "pale blue glass, rounded panels, soft webcore",
  "variables": {
    "--bg-base": "#dcecff",
    "--bg-soft": "#f7fbff",
    "--bg-spot-a": "rgba(151, 205, 255, 0.55)",
    "--bg-spot-b": "rgba(229, 237, 255, 0.78)",
    "--bg-lines": "rgba(116, 151, 190, 0.14)",
    "--panel-bg": "rgba(255, 255, 255, 0.82)",
    "--panel-bg-strong": "rgba(255, 255, 255, 0.95)",
    "--panel-muted": "rgba(244, 249, 255, 0.72)",
    "--panel-border": "rgba(166, 178, 196, 0.68)",
    "--panel-border-strong": "rgba(134, 153, 180, 0.82)",
    "--text": "#77859a",
    "--text-strong": "#5c6f8c",
    "--text-faint": "#9aa9bb",
    "--accent": "#8fc9ff",
    "--accent-2": "#c6b7ff",
    "--accent-3": "#ff94d4",
    "--ok": "#59b879",
    "--danger": "#e35d82",
    "--warning": "#bf9845",
    "--shadow": "rgba(79, 98, 124, 0.25)",
    "--glow": "rgba(143, 201, 255, 0.48)",
    "--radius-xl": "24px",
    "--radius-lg": "18px",
    "--radius-md": "12px",
    "--radius-sm": "8px",
    "--font-ui": "\"Trebuchet MS\", \"Segoe UI\", Arial, sans-serif",
    "--font-mono": "\"Lucida Console\", Monaco, Consolas, monospace",
    "--font-display": "\"Trebuchet MS\", \"Segoe UI\", Arial, sans-serif"
  }
}
